template/__init__.py
template/test_template.py
pypi_template_castellani_davide-1.0.dist-info/METADATA
pypi_template_castellani_davide-1.0.dist-info/WHEEL
pypi_template_castellani_davide-1.0.dist-info/top_level.txt
pypi_template_castellani_davide-1.0.dist-info/zip-safe
pypi_template_castellani_davide-1.0.dist-info/RECORD
