Metadata-Version: 2.1
Name: pypi-template-castellani-davide
Version: 1.0
Summary: This is the template for PyPi projects.
Home-page: https://github.com/CastellaniDavide/pypi-template
Author: CastellaniDavide
Author-email: help@castellanidavide.it
License: GNU
Platform: linux_distibution
Requires-Python: >=3.7
